factory/__main__.py
factory/gruvbox-mix.txt
factory/gruvbox-pink.txt
factory/gruvbox-white.txt
gruvbox_factory-2.0.0.dist-info/LICENSE
gruvbox_factory-2.0.0.dist-info/METADATA
gruvbox_factory-2.0.0.dist-info/WHEEL
gruvbox_factory-2.0.0.dist-info/entry_points.txt
gruvbox_factory-2.0.0.dist-info/top_level.txt
gruvbox_factory-2.0.0.dist-info/RECORD
