Metadata-Version: 2.2
Name: gruvbox-factory
Version: 2.0.0
Summary: convert any image to the gruvbox pallete!
Author-email: Paulo Pacitti <ppacitti@outlook.com>
License: MIT
Project-URL: Homepage, https://github.com/paulopacitti/gruvbox-factory
Project-URL: Bug Tracker, https://github.com/paulopacitti/gruvbox-factory/issues
Keywords: gruvbox,cli,gruvbox-factory,wallpaper,image,image-go-nord,palette,factory
Classifier: Programming Language :: Python :: 3
Classifier: License :: OSI Approved :: MIT License
Classifier: Operating System :: OS Independent
Requires-Python: >=3.13.1
License-File: LICENSE
Requires-Dist: certifi==2025.1.31
Requires-Dist: charset-normalizer==3.4.1
Requires-Dist: ffmpeg-python==0.2.0
Requires-Dist: future==1.0.0
Requires-Dist: idna==3.10
Requires-Dist: image-go-nord==1.2.0
Requires-Dist: markdown-it-py==3.0.0
Requires-Dist: mdurl==0.1.2
Requires-Dist: numpy==2.2.2
Requires-Dist: pick==2.4.0
Requires-Dist: pillow==11.1.0
Requires-Dist: Pygments==2.19.1
Requires-Dist: requests==2.32.3
Requires-Dist: rich==13.9.4
Requires-Dist: setuptools==75.8.0
Requires-Dist: urllib3==2.3.0
